[
    {
        "name": "tilt",
        "owner": {
            "login": "windmilleng"
        },
        "full_name": "windmilleng/tilt",
        "forks_count": "13",
        "stargazers_count": "786",
        "language": "Go",
        "repositoryDescription": "Local Kubernetes development with no stress"
    },
    {
        "name": "uncaptcha2",
        "owner": {
            "login": "ecthros"
        },
        "full_name": "ecthros/uncaptcha2",
        "forks_count": "192",
        "stargazers_count": "2539",
        "language": "Python",
        "repositoryDescription": "defeating the latest version of ReCaptcha with 91% accuracy"
    },
    {
        "name": "deeptraffic",
        "owner": {
            "login": "lexfridman"
        },
        "full_name": "lexfridman/deeptraffic",
        "forks_count": "45",
        "stargazers_count": "335",
        "language": "JavaScript",
        "repositoryDescription": "DeepTraffic is a deep reinforcement learning competition, part of the MIT Deep Learning series."
    },
    {
        "name": "litecli",
        "owner": {
            "login": "dbcli"
        },
        "full_name": "dbcli/litecli",
        "forks_count": "5",
        "stargazers_count": "400",
        "language": "Python",
        "repositoryDescription": "CLI for SQLite Databases with auto-completion and syntax highlighting"
    },
    {
        "name": "homemade-machine-learning",
        "owner": {
            "login": "trekhleb"
        },
        "full_name": "trekhleb/homemade-machine-learning",
        "forks_count": "1169",
        "stargazers_count": "6227",
        "language": "Jupyter Notebook",
        "repositoryDescription": "🤖\nPython examples of popular machine learning algorithms with interactive Jupyter demos and math being explained"
    },
    {
        "name": "12306",
        "owner": {
            "login": "testerSunshine"
        },
        "full_name": "testerSunshine/12306",
        "forks_count": "417",
        "stargazers_count": "1248",
        "language": "Python",
        "repositoryDescription": "12306智能刷票，订票"
    },
    {
        "name": "doom-fire-algorithm",
        "owner": {
            "login": "filipedeschamps"
        },
        "full_name": "filipedeschamps/doom-fire-algorithm",
        "forks_count": "14",
        "stargazers_count": "208",
        "language": "JavaScript",
        "repositoryDescription": "Fire effect from Doom implemented in plain JavaScript"
    },
    {
        "name": "JavaGuide",
        "owner": {
            "login": "Snailclimb"
        },
        "full_name": "Snailclimb/JavaGuide",
        "forks_count": "5448",
        "stargazers_count": "19011",
        "language": "Java",
        "repositoryDescription": "【Java学习+面试指南】 一份涵盖大部分Java程序员所需要掌握的核心知识。"
    },
    {
        "name": "noria",
        "owner": {
            "login": "mit-pdos"
        },
        "full_name": "mit-pdos/noria",
        "forks_count": "26",
        "stargazers_count": "719",
        "language": "Rust",
        "repositoryDescription": "Dynamically changing, partially-stateful data-flow for web application backends."
    },
    {
        "name": "Menu",
        "owner": {
            "login": "TwoLivesLeft"
        },
        "full_name": "TwoLivesLeft/Menu",
        "forks_count": "15",
        "stargazers_count": "418",
        "language": "Swift",
        "repositoryDescription": "The iOS Menu"
    },
    {
        "name": "awesome-interview-questions",
        "owner": {
            "login": "MaximAbramchuck"
        },
        "full_name": "MaximAbramchuck/awesome-interview-questions",
        "forks_count": "3015",
        "stargazers_count": "24627",
        "repositoryDescription": "A curated awesome list of lists of interview questions. Feel free to contribute!\n🎓"
    },
    {
        "name": "CS-Notes",
        "owner": {
            "login": "CyC2018"
        },
        "full_name": "CyC2018/CS-Notes",
        "forks_count": "14082",
        "stargazers_count": "45910",
        "repositoryDescription": "📚\nComputer Science Learning Notes"
    },
    {
        "name": "algorithms",
        "owner": {
            "login": "jeffgerickson"
        },
        "full_name": "jeffgerickson/algorithms",
        "forks_count": "250",
        "stargazers_count": "2022",
        "repositoryDescription": "Bug-tracking for Jeff's algorithms book, notes, etc."
    },
    {
        "name": "fbt",
        "owner": {
            "login": "facebookincubator"
        },
        "full_name": "facebookincubator/fbt",
        "forks_count": "52",
        "stargazers_count": "1900",
        "language": "JavaScript",
        "repositoryDescription": "A JavaScript Internationalization Framework"
    },
    {
        "name": "string-similarity",
        "owner": {
            "login": "aceakash"
        },
        "full_name": "aceakash/string-similarity",
        "forks_count": "31",
        "stargazers_count": "730",
        "language": "JavaScript",
        "repositoryDescription": "Finds degree of similarity between two strings, based on Dice's Coefficient, which is mostly better than Levenshtein distance."
    },
    {
        "name": "learn-json-web-tokens",
        "owner": {
            "login": "dwyl"
        },
        "full_name": "dwyl/learn-json-web-tokens",
        "forks_count": "203",
        "stargazers_count": "3142",
        "language": "JavaScript",
        "repositoryDescription": "🔐\nLearn how to use JSON Web Token (JWT) to secure your next Web App! (Tutorial/Example with Tests!!)"
    },
    {
        "name": "Here",
        "owner": {
            "login": "caijinyc"
        },
        "full_name": "caijinyc/Here",
        "forks_count": "25",
        "stargazers_count": "206",
        "language": "JavaScript",
        "repositoryDescription": "Here Music 一个 使用 Electron + React 开发的音乐客户端"
    },
    {
        "name": "edge-connect",
        "owner": {
            "login": "knazeri"
        },
        "full_name": "knazeri/edge-connect",
        "forks_count": "51",
        "stargazers_count": "279",
        "language": "Python",
        "repositoryDescription": "EdgeConnect: Generative Image Inpainting with Adversarial Edge Learning. https://arxiv.org/abs/1901.00212"
    },
    {
        "name": "dragonboat",
        "owner": {
            "login": "lni"
        },
        "full_name": "lni/dragonboat",
        "forks_count": "45",
        "stargazers_count": "636",
        "language": "Go",
        "repositoryDescription": "Dragonboat is a feature complete and high performance multi-group Raft library in Go."
    },
    {
        "name": "advanced-java",
        "owner": {
            "login": "doocs"
        },
        "full_name": "doocs/advanced-java",
        "forks_count": "744",
        "stargazers_count": "4337",
        "language": "Java",
        "repositoryDescription": "😮\n互联网 Java 工程师进阶知识完全扫盲"
    },
    {
        "name": "gaia",
        "owner": {
            "login": "gaia-pipeline"
        },
        "full_name": "gaia-pipeline/gaia",
        "forks_count": "106",
        "stargazers_count": "2936",
        "language": "Go",
        "repositoryDescription": "Build powerful pipelines in any programming language."
    },
    {
        "name": "pwc",
        "owner": {
            "login": "zziz"
        },
        "full_name": "zziz/pwc",
        "forks_count": "836",
        "stargazers_count": "7633",
        "repositoryDescription": "Papers with code. Sorted by stars. Updated weekly."
    },
    {
        "name": "practicalAI",
        "owner": {
            "login": "GokuMohandas"
        },
        "full_name": "GokuMohandas/practicalAI",
        "forks_count": "1799",
        "stargazers_count": "12727",
        "language": "Jupyter Notebook",
        "repositoryDescription": "📚\nA practical approach to learning machine learning."
    },
    {
        "name": "react-with-gesture",
        "owner": {
            "login": "drcmda"
        },
        "full_name": "drcmda/react-with-gesture",
        "forks_count": "26",
        "stargazers_count": "586",
        "language": "JavaScript",
        "repositoryDescription": "👇\nBread n butter utility for component-tied mouse/touch gestures in React"
    },
    {
        "name": "omniclone",
        "owner": {
            "login": "jfet97"
        },
        "full_name": "jfet97/omniclone",
        "forks_count": "",
        "stargazers_count": "106",
        "language": "JavaScript",
        "repositoryDescription": "An isomorphic and configurable javascript utility for objects deep cloning."
    }
]